targpg/__init__.py
targpg/__main__.py
targpg/meta.py
targpg/parser.py
targpg/targpg.py
test/__init__.py
test/test_targpg.py
targpg-1.1.0.dist-info/LICENSE
targpg-1.1.0.dist-info/METADATA
targpg-1.1.0.dist-info/WHEEL
targpg-1.1.0.dist-info/top_level.txt
targpg-1.1.0.dist-info/RECORD
