Metadata-Version: 2.1
Name: targpg
Version: 1.1.0
Summary: manage secure archive containing sensative docs
Home-page: https://github.com/spslater/targpg
Author: Sean Slater
Author-email: seanslater@whatno.io
License: MIT License
Keywords: filesystem files secure tar gpg
Classifier: Development Status :: 4 - Beta
Classifier: Programming Language :: Python :: 3
Classifier: Programming Language :: Python :: 3.11
Classifier: Programming Language :: Python :: 3.10
Classifier: Programming Language :: Python :: 3.9
Classifier: Programming Language :: Python :: 3.8
Classifier: Programming Language :: Python :: 3.7
Classifier: Programming Language :: Python :: 3.6
Classifier: Operating System :: OS Independent
Classifier: License :: OSI Approved :: MIT License
Classifier: Topic :: Utilities
Classifier: Topic :: System :: Filesystems
Classifier: Environment :: Console
Requires-Python: >=3.6
License-File: LICENSE
